[
    {
        "id": "egov-participation",
        "title": "Συμμετοχική Διακυβέρνηση",
        "description": "Λογισμικό που προάγει τη διαφάνεια και επιτρέπει στους πολίτες να συμμετέχουν ενεργά στη λήψη αποφάσεων.",
        "subcategories": [
            {
                "id": "decidim-gov",
                "title": "Decidim",
                "description": "Πλατφόρμα συμμετοχικής δημοκρατίας για ψηφοφορίες, τοποθετήσεις πολιτών και κατάρτιση συμμετοχικού προϋπολογισμού.",
                "commercial_equivalent": "Κλειστά συστήματα διαβούλευσης",
                "url": "https://decidim.org/"
            },
            {
                "id": "consul-gov",
                "title": "Consul Democracy",
                "description": "Πρωτοποριακή λύση ανοιχτού λογισμικού για τη συμμετοχή των πολιτών στη λήψη αποφάσεων, σε χρήση από μεγάλες πόλεις παγκοσμίως.",
                "commercial_equivalent": "CitizenLab (Proprietary)",
                "url": "https://consuldemocracy.org/"
            },
            {
                "id": "globaleaks-gov",
                "title": "GlobaLeaks",
                "description": "Πλατφόρμα για την ασφαλή και ανώνυμη υποβολή καταγγελιών, διασφαλίζοντας την προστασία των πληροφοριοδοτών.",
                "commercial_equivalent": "Gotcha (Proprietary)",
                "url": "https://www.globaleaks.org/"
            },
            {
                "id": "mastodon-gov",
                "title": "Mastodon",
                "description": "Αποκεντρωμένη πλατφόρμα ενημέρωσης και επικοινωνίας που επιτρέπει σε δημόσιους φορείς να διατηρούν τη δική τους παρουσία στα μέσα κοινωνικής δικτύωσης με απόλυτη κυριότητα των δεδομένων.",
                "commercial_equivalent": "X (Twitter)",
                "url": "https://joinmastodon.org"
            },
            {
                "id": "securedrop-gov",
                "title": "SecureDrop",
                "description": "Σύστημα υποβολής ανώνυμων πληροφοριών με υψηλά επίπεδα ασφάλειας για ευαίσθητα δεδομένα.",
                "commercial_equivalent": "Ιδιωτικά συστήματα καταγγελιών",
                "url": "https://securedrop.org/"
            },
            {
                "id": "fider-gov",
                "title": "Fider",
                "description": "Πλατφόρμα για τη συλλογή και οργάνωση προτάσεων και ανατροφοδότησης από τους χρήστες/πολίτες.",
                "commercial_equivalent": "UserVoice",
                "url": "https://fider.io/"
            },
            {
                "id": "cachet-gov",
                "title": "Cachet",
                "description": "Σελίδα κατάστασης (status page) ανοικτού κώδικα για την ενημέρωση των χρηστών σχετικά με τη διαθεσιμότητα των υπηρεσιών.",
                "commercial_equivalent": "Statuspage.io",
                "url": "https://cachethq.io/"
            }
        ]
    },
    {
        "id": "open-data-portals",
        "title": "Ανοιχτά Δεδομένα",
        "description": "Εργαλεία για τη δημιουργία πυλών πρόσβασης και διαχείρισης διοικητικών δεδομένων.",
        "subcategories": [
            {
                "id": "ckan-gov",
                "title": "CKAN",
                "description": "Το κορυφαίο σύστημα παγκοσμίως για την αποθήκευση, διανομή και διαχείριση ανοιχτών δεδομένων.",
                "commercial_equivalent": "Socrata",
                "url": "https://ckan.org/"
            },
            {
                "id": "dcan-gov",
                "title": "DCAN",
                "description": "Εργαλείο ανοιχτού κώδικα για τη δημιουργία πυλών πρόσβασης σε διοικητικά δεδομένα.",
                "commercial_equivalent": "Custom Data Portals",
                "url": "https://getdkan.org/"
            },
            {
                "id": "plausible-gov",
                "title": "Plausible Analytics",
                "description": "Εργαλείο ανάλυσης επισκεψιμότητας δημόσιων ιστοτόπων που σέβεται απόλυτα την ιδιωτικότητα των πολιτών χωρίς τη χρήση cookies παρακολούθησης.",
                "commercial_equivalent": "Custom Analytics Solutions",
                "url": "https://plausible.io/"
            },
            {
                "id": "questdb-gov",
                "title": "QuestDB",
                "description": "Βάση δεδομένων χρονοσειρών υψηλής απόδοσης, κατάλληλη για την επεξεργασία μεγάλου όγκου δεδομένων από δημόσιες υποδομές και δίκτυα αισθητήρων σε πραγματικό χρόνο.",
                "commercial_equivalent": "Kdb+",
                "url": "https://questdb.io/"
            },
            {
                "id": "openfisca-gov",
                "title": "OpenFisca",
                "description": "Πλατφόρμα προσομοίωσης φορολογικής και κοινωνικής πολιτικής για την ανάλυση επιπτώσεων νομοθετικών αλλαγών.",
                "commercial_equivalent": "Custom Proprietary Simulation Software",
                "url": "https://openfisca.org/"
            }
        ]
    },
    {
        "id": "gov-infrastructure",
        "title": "Υποδομές & Διαλειτουργικότητα",
        "description": "Λύσεις για τη συνεργασία, τη διαχείριση εγγράφων και τις κρίσιμες βάσεις δεδομένων του δημόσιου τομέα.",
        "subcategories": [
            {
                "id": "nextcloud-gov",
                "title": "Nextcloud",
                "description": "Ολοκληρωμένη πλατφόρμα για φιλοξενία, διαμοιρασμό αρχείων και συνεργατική επεξεργασία εγγράφων.",
                "commercial_equivalent": "MS Teams, Google Docs",
                "url": "https://nextcloud.com/"
            },
            {
                "id": "argos-translate-gov",
                "title": "Argos Translate",
                "description": "Ανοικτό σύστημα αυτόματης μετάφρασης βασισμένο σε νευρωνικά δίκτυα για την ενίσχυση της πολυγλωσσίας και της προσβασιμότητας στις δημόσιες ψηφιακές υπηρεσίες.",
                "commercial_equivalent": "Custom Translation Services",
                "url": "https://www.argosopentech.com/"
            },
            {
                "id": "libreoffice-gov",
                "title": "LibreOffice",
                "description": "Σουίτα εφαρμογών γραφείου που προσφέρει δημοσιονομική υπευθυνότητα με υποπολλαπλάσιο κόστος.",
                "commercial_equivalent": "Microsoft Office",
                "url": "https://el.libreoffice.org/"
            },
            {
                "id": "openfaas-gov",
                "title": "OpenFaaS",
                "description": "Πλαίσιο για την εκτέλεση συναρτήσεων ως υπηρεσιών (Serverless), επιτρέποντας στους δημόσιους φορείς να αναπτύσσουν κλιμακούμενες μικροϋπηρεσίες με αποδοτικό τρόπο.",
                "commercial_equivalent": "AWS Lambda, Heroku",
                "url": "https://www.openfaas.com/"
            },
            {
                "id": "postgresql-gov",
                "title": "PostgreSQL",
                "description": "Η πιο προηγμένη βάση δεδομένων ανοιχτού κώδικα για κρίσιμες δημόσιες εφαρμογές.",
                "commercial_equivalent": "Oracle Database",
                "url": "https://www.postgresql.org/"
            },
            {
                "id": "wordpress-gov",
                "title": "WordPress",
                "description": "Σύστημα Διαχείρισης Περιεχομένου (CMS) για την παρουσίαση και ενημέρωση των δημόσιων ιστότοπων.",
                "commercial_equivalent": "SAP Enterprise Portal",
                "url": "https://wordpress.org/"
            },
            {
                "id": "winscp-gov",
                "title": "WinSCP",
                "description": "Εργαλείο ασφαλούς μεταφοράς δεδομένων (SFTP/SCP) για τη διαχείριση κυβερνητικών διακομιστών και την προστασία των πληροφοριών κατά τη μεταφορά.",
                "commercial_equivalent": "Secure File Transfer Clients",
                "url": "https://winscp.net/eng/index.php"
            },
            {
                "id": "keycloak-gov",
                "title": "Keycloak",
                "description": "Διαχείριση ταυτότητας και πρόσβασης (SSO) για την ασφαλή ταυτοποίηση στις δημόσιες υπηρεσίες.",
                "commercial_equivalent": "Okta, Auth0",
                "url": "https://www.keycloak.org/"
            },
            {
                "id": "gnucomm-gov",
                "title": "Gnucomm",
                "description": "Το κεντρικό πρόγραμμα τηλεπικοινωνιών του εγχειρήματος GNU, σχεδιασμένο για την παροχή ελεύθερων τηλεπικοινωνιακών υποδομών.",
                "commercial_equivalent": "Proprietary Telecom Stacks",
                "url": "https://www.gnu.org/software/gnucomm/"
            },
            {
                "id": "jami-gov",
                "title": "Jami",
                "description": "Κατανεμημένο σύστημα επικοινωνίας χωρίς κεντρικό διακομιστή, ιδανικό για ασφαλείς ενδοκυβερνητικές συνομιλίες με πλήρη κυριαρχία δεδομένων.",
                "commercial_equivalent": "Secure IP Telephony",
                "url": "https://www.gnu.org/software/jami/"
            },
            {
                "id": "rocket-chat-gov",
                "title": "Rocket.Chat",
                "description": "Μια πλήρως παραμετροποιήσιμη πλατφόρμα επικοινωνίας που επιτρέπει σε δημόσιους φορείς να αντικαταστήσουν κλειστά εμπορικά συστήματα, διατηρώντας τον πλήρη έλεγχο των συνομιλιών και των αρχείων τους.",
                "commercial_equivalent": "Slack",
                "url": "https://rocket.chat/"
            },
            {
                "id": "mattermost-gov",
                "title": "Mattermost",
                "description": "Λύση ομαδικής επικοινωνίας και διαχείρισης ροών εργασίας (workflow), σχεδιασμένη για περιβάλλοντα με υψηλές απαιτήσεις ασφαλείας και ιδιωτικότητας στον δημόσιο τομέα.",
                "commercial_equivalent": "Slack, Microsoft Teams",
                "url": "https://mattermost.com"
            },
            {
                "id": "zulip-gov",
                "title": "Zulip",
                "description": "Πλατφόρμα ομαδικής συνομιλίας που οργανώνει τις συζητήσεις σε θέματα (threading), διευκολύνοντας την παρακολούθηση σύνθετων υπηρεσιακών θεμάτων και τη λήψη αποφάσεων.",
                "commercial_equivalent": "Slack",
                "url": "https://zulip.com/"
            },
            {
                "id": "element-gov",
                "title": "Element",
                "description": "Ασφαλής εφαρμογή επικοινωνίας βασισμένη στο ανοικτό πρωτόκολλο Matrix, που επιτρέπει τη διαλειτουργικότητα μεταξύ διαφορετικών κυβερνητικών τμημάτων με κρυπτογράφηση άκρου-προς-άκρο.",
                "commercial_equivalent": "Slack, Discord",
                "url": "https://element.io/"
            },
            {
                "id": "xvid-gov",
                "title": "Xvid",
                "description": "Ένας κωδικοποιητής βίντεο υψηλής απόδοσης που ακολουθεί το πρότυπο MPEG-4, εξασφαλίζοντας τη συμβατότητα και τη συμπίεση ψηφιακού περιεχομένου.",
                "commercial_equivalent": "DivX",
                "url": "https://labs.xvid.com/"
            },
            {
                "id": "theora-gov",
                "title": "Theora",
                "description": "Ένα ελεύθερο και ανοικτό format συμπίεσης βίντεο που δεν απαιτεί δικαιώματα χρήσης, ιδανικό για τη διανομή δημόσιου οπτικοακουστικού περιεχομένου.",
                "commercial_equivalent": "Proprietary Video Codecs",
                "url": "https://www.theora.org/"
            },
            {
                "id": "drupal-gov",
                "title": "Drupal",
                "description": "Ένα από τα κορυφαία συστήματα διαχείρισης περιεχομένου (CMS) στον κόσμο, με δυνατότητες ενσωμάτωσης τεχνητής νοημοσύνης και απόλυτο έλεγχο χωρίς εξάρτηση από προμηθευτές.",
                "commercial_equivalent": "Adobe Experience Manager, Sitecore",
                "url": "https://new.drupal.org/home"
            },
            {
                "id": "alfresco-gov",
                "title": "Alfresco",
                "description": "Εταιρικού επιπέδου πλατφόρμα για την αυτοματοποίηση ροών εργασίας και τη διαχείριση εγγράφων σε δημόσιους οργανισμούς με υψηλές απαιτήσεις διακυβέρνησης.",
                "commercial_equivalent": "OpenText",
                "url": "https://www.hyland.com/en/solutions/products/alfresco-platform"
            },
            {
                "id": "stalwart-gov",
                "title": "Stalwart Mail Server",
                "description": "Ασφαλής και κλιμακούμενη υποδομή ηλεκτρονικού ταχυδρομείου για δημόσιους φορείς, που εξασφαλίζει την κυριαρχία των δεδομένων αλληλογραφίας.",
                "commercial_equivalent": "Enterprise Grade Mail Servers",
                "url": "https://stalw.art/"
            },
            {
                "id": "dokuwiki-gov",
                "title": "DokuWiki",
                "description": "Ένα εξαιρετικά ευέλικτο και εύχρηστο λογισμικό Wiki που δεν απαιτεί βάση δεδομένων, ιδανικό για την τεκμηρίωση υπηρεσιακών διαδικασιών και εγχειριδίων.",
                "commercial_equivalent": "Confluence, Microsoft SharePoint",
                "url": "https://www.dokuwiki.org/dokuwiki"
            },
            {
                "id": "zammad-gov",
                "title": "Zammad",
                "description": "Σύστημα διαχείρισης αιτημάτων πολιτών και εσωτερικής υποστήριξης για δημόσιους φορείς, προσφέροντας διαφάνεια και οργάνωση στην επικοινωνία.",
                "commercial_equivalent": "Proprietary Helpdesk Systems",
                "url": "https://zammad.com/en"
            },
            {
                "id": "mediacms-gov",
                "title": "MediaCMS",
                "description": "Μια πλήρης πλατφόρμα διαχείρισης περιεχομένου βίντεο που επιτρέπει σε οργανισμούς να δημιουργήσουν τη δική τους εσωτερική υπηρεσία τύπου YouTube.",
                "commercial_equivalent": "Vimeo OTT, Microsoft Stream",
                "url": "https://mediacms.io/"
            },
            {
                "id": "tube-gov",
                "title": "Tube",
                "description": "Εργαλείο για τη διαχείριση συλλογών βίντεο και ροών RSS, εστιάζοντας στην οργάνωση περιεχομένου.",
                "commercial_equivalent": "Feedly",
                "url": "https://git.mills.io/prologic/tube"
            },
            {
                "id": "caddy-gov",
                "title": "Caddy",
                "description": "Ασφαλής εξυπηρετητής ιστού για δημόσιες υπηρεσίες, που εγγυάται την κρυπτογραφημένη επικοινωνία (HTTPS) χωρίς πολύπλοκες ρυθμίσεις.",
                "commercial_equivalent": "Proprietary Web Servers",
                "url": "https://caddyserver.com/"
            },
            {
                "id": "kubernetes-gov",
                "title": "Kubernetes",
                "description": "Πλατφόρμα ενορχήστρωσης containers για τη δημιουργία κλιμακούμενων και σταθερών δημόσιων ψηφιακών υπηρεσιών με υψηλή διαθεσιμότητα.",
                "commercial_equivalent": "Proprietary Orchestration Tools",
                "url": "https://kubernetes.io/"
            },
            {
                "id": "shlink-gov",
                "title": "Shlink",
                "description": "Εργαλείο διαχείρισης σύντομων συνδέσμων για κυβερνητικούς ιστότοπους, διασφαλίζοντας ότι τα δεδομένα των πολιτών παραμένουν σε εγχώριες υποδομές.",
                "commercial_equivalent": "Bitly Enterprise",
                "url": "https://shlink.io/"
            },
            {
                "id": "php-dynamic-qr-daily",
                "title": "PHP Dynamic QR Code",
                "description": "Εφαρμογή για τη δημιουργία και διαχείριση δυναμικών κωδικών QR που μπορούν να τροποποιηθούν μετά την εκτύπωση.",
                "commercial_equivalent": "QR Code Generator (Paid)",
                "url": "https://github.com/giandonatoinverso/PHP-Dynamic-Qr-code"
            },
            {
                "id": "gnu-health-gov",
                "title": "GNU Health",
                "description": "Ένα ολοκληρωμένο οικοσύστημα ψηφιακής υγείας που συνδυάζει την κοινωνική ιατρική με την προηγμένη πληροφορική υγείας για δημόσιες νοσοκομειακές υποδομές. ",
                "commercial_equivalent": "Proprietary HIS (Hospital Information Systems) ",
                "url": "https://www.gnu.org/health/ "
            },
            {
                "id": "openemr-gov",
                "title": "OpenEMR",
                "description": "Το κορυφαίο λογισμικό ανοικτού κώδικα παγκοσμίως για τη διαχείριση ηλεκτρονικών ιατρικών φακέλων (EMR) και ιατρικών πρακτικών. ",
                "commercial_equivalent": "Proprietary EMR Solutions ",
                "url": "https://www.open-emr.org/ "
            },
            {
                "id": "openmrs-edu",
                "title": "OpenMRS",
                "description": "Μια πλατφόρμα ηλεκτρονικών ιατρικών αρχείων που αναπτύσσεται από μια παγκόσμια κοινότητα, θέτοντας τα πρότυπα για την ψηφιακή υγεία σε ερευνητικό και ακαδημαϊκό επίπεδο. ",
                "commercial_equivalent": "Proprietary Medical Record Systems ",
                "url": "https://openmrs.org/ "
            },
            {
                "id": "orthanc-gov",
                "title": "Orthanc",
                "description": "Ένας ελαφρύς και ελεύθερος διακομιστής DICOM για τη διαχείριση και αρχειοθέτηση ιατρικών εικόνων (ακτινογραφίες, αξονικές κ.α.). ",
                "commercial_equivalent": "Proprietary PACS Systems ",
                "url": "https://www.orthanc-server.com/ "
            },
            {
                "id": "sheltermanager-biz",
                "title": "Animal Shelter Manager",
                "description": "Ολοκληρωμένη λύση για καταφύγια ζώων και ομάδες διάσωσης, με εργαλεία για την παρακολούθηση της ιατρικής φροντίδας, της υιοθεσίας, των οικονομικών και των εργασιών του προσωπικού.",
                "commercial_equivalent": "Shelterluv, PetPoint",
                "url": "https://sheltermanager.com/site/en_home.html"
            },
            {
                "id": "plone-gov",
                "title": "Plone",
                "description": "Σύστημα διαχείρισης περιεχομένου υψηλής ασφάλειας, που χρησιμοποιείται συχνά για ενδοδίκτυα μεγάλων δημόσιων οργανισμών.",
                "commercial_equivalent": "Microsoft SharePoint",
                "url": "https://plone.org/"
            },
            {
                "id": "paperless-gov",
                "title": "Paperless-ngx",
                "description": "Σύστημα διαχείρισης εγγράφων που σαρώνει, αρχειοθετεί και ευρετηριάζει φυσικά έγγραφα, προωθώντας τη μείωση της χρήσης χαρτιού.",
                "commercial_equivalent": "Proprietary DMS",
                "url": "https://github.com/paperless-ngx/paperless-ngx"
            },
            {
                "id": "bacula-gov",
                "title": "Bacula",
                "description": "Σύστημα αντιγράφων ασφαλείας επιπέδου οργανισμού, με υποστήριξη για μαγνητοταινίες και μεγάλους παρόχους cloud.",
                "commercial_equivalent": "Veritas NetBackup",
                "url": "https://www.bacula.org/"
            },
            {
                "id": "projectsend-gov",
                "title": "ProjectSend",
                "description": "Εφαρμογή για την ασφαλή αποστολή αρχείων σε πελάτες ή συνεργάτες, με δυνατότητα διαχείρισης χρηστών και πλήρη καταγραφή ενεργειών.",
                "commercial_equivalent": "ShareFile",
                "url": "https://www.projectsend.org/"
            },
            {
                "id": "bareos-gov",
                "title": "Bareos",
                "description": "Ισχυρό λογισμικό αντιγράφων ασφαλείας και ανάκτησης δεδομένων για ετερογενή δίκτυα και σύνθετες υποδομές.",
                "commercial_equivalent": "Veritas Backup Exec",
                "url": "https://www.bareos.com/"
            },
            {
                "id": "restic-gov",
                "title": "Restic",
                "description": "Γρήγορο και ασφαλές πρόγραμμα αντιγράφων ασφαλείας που υποστηρίζει πολλούς παρόχους αποθήκευσης και κρυπτογράφηση.",
                "commercial_equivalent": "Acronis",
                "url": "https://restic.net/"
            }
        ]
    },
    {
        "id": "gov-gis-security",
        "title": "GIS & Ασφάλεια",
        "description": "Γεωγραφικά συστήματα και εργαλεία προστασίας των ψηφιακών υποδομών του κράτους.",
        "subcategories": [
            {
                "id": "qgis-gov",
                "title": "QGIS",
                "description": "Ανάλυση και οπτικοποίηση γεωγραφικών δεδομένων για δήμους και δημόσιους φορείς.",
                "commercial_equivalent": "ESRI ArcGIS",
                "url": "https://www.qgis.org/"
            },
            {
                "id": "pfsense-gov",
                "title": "pfSense",
                "description": "Λογισμικό τείχους ασφαλείας (Firewall) και δρομολόγησης επιπέδου οργανισμού.",
                "commercial_equivalent": "Cisco ASA, Juniper",
                "url": "https://www.pfsense.org/"
            },
            {
                "id": "shorewall-gov",
                "title": "Shorewall",
                "description": "Εργαλείο υψηλού επιπέδου για τη διαμόρφωση τείχους προστασίας (Netfilter).",
                "commercial_equivalent": "Norton Internet Security",
                "url": "https://shorewall.org/"
            },
            {
                "id": "ufw-gov",
                "title": "UFW",
                "description": "Εύχρηστο εργαλείο διαχείρισης τείχους ασφαλείας, προεπιλεγμένο στο Ubuntu.",
                "commercial_equivalent": "Norton Internet Security",
                "url": "https://help.ubuntu.com/community/UFW"
            },
            {
                "id": "scilab-gov",
                "title": "SciLab",
                "description": "Εργαλείο μαθηματικών υπολογισμών και ανάλυσης δεδομένων για δημόσιους ερευνητικούς φορείς και οργανισμούς που απαιτούν σύνθετες προσομοιώσεις.",
                "commercial_equivalent": "MATLAB",
                "url": "https://www.scilab.org/"
            },
            {
                "id": "libgcrypt-gov",
                "title": "Libgcrypt",
                "description": "Μια γενική βιβλιοθήκη κρυπτογραφίας βασισμένη στον κώδικα του GnuPG, η οποία παρέχει θεμελιώδη δομικά στοιχεία για την ασφάλεια των δημόσιων ψηφιακών υποδομών.",
                "commercial_equivalent": "Proprietary Crypto Libraries",
                "url": "https://gnupg.org/software/libgcrypt/"
            },
            {
                "id": "enigmail-gov",
                "title": "Enigmail",
                "description": "Επέκταση ασφαλείας για το Thunderbird που ενσωματώνει την κρυπτογράφηση PGP, απαραίτητη για την εμπιστευτική υπηρεσιακή αλληλογραφία.",
                "commercial_equivalent": "Secure Email Gateways",
                "url": "http://www.enigmail.net/home/index.php"
            },
            {
                "id": "leon-gov",
                "title": "Leon",
                "description": "Ένας ανοικτός προσωπικός βοηθός (AI) που μπορεί να φιλοξενηθεί σε τοπικούς διακομιστή (self-hosted), επιτρέποντας στους δημόσιους φορείς να αυτοματοποιούν εργασίες χωρίς να εκθέτουν δεδομένα σε εξωτερικά clouds.",
                "commercial_equivalent": "Siri, Google Assistant",
                "url": "https://getleon.ai/"
            },
            {
                "id": "torbirdy-gov",
                "title": "TorBirdy",
                "description": "Εξειδικευμένο εργαλείο που ρυθμίζει το Mozilla Thunderbird ώστε να δρομολογεί την αλληλογραφία μέσω του δικτύου Tor, εξασφαλίζοντας την ανωνυμία των κυβερνητικών επικοινωνιών.",
                "commercial_equivalent": "Secure Email Routing",
                "url": "https://trac.torproject.org/projects/tor/wiki/torbirdy"
            },
            {
                "id": "privoxy-gov",
                "title": "Privoxy",
                "description": "Εργαλείο φιλτραρίσματος περιεχομένου και προστασίας ιδιωτικότητας σε επίπεδο δικτύου, απαραίτητο για τη θωράκιση των σταθμών εργασίας δημόσιων υπαλλήλων.",
                "commercial_equivalent": "Enterprise Web Filtering",
                "url": "https://www.privoxy.org/"
            },
            {
                "id": "gnutls-gov",
                "title": "GnuTLS",
                "description": "Μια ασφαλής βιβλιοθήκη που υλοποιεί τα πρωτόκολλα TLS και SSL, παρέχοντας το απαραίτητο επίπεδο ασφαλείας για την κρυπτογράφηση των δημόσιων ψηφιακών επικοινωνιών.",
                "commercial_equivalent": "Proprietary SSL Libraries",
                "url": "https://www.gnu.org/software/gnutls/"
            },
            {
                "id": "foremost-gov",
                "title": "Foremost",
                "description": "Εξειδικευμένο εργαλείο εγκληματολογικής ανάλυσης (forensics) για την ανάκτηση χαμένων αρχείων με βάση τις κεφαλίδες και τις δομές των δεδομένων τους.",
                "commercial_equivalent": "Specialized Data Recovery Tools",
                "url": "https://foremost.sourceforge.net/"
            },
            {
                "id": "qtparted-gov",
                "title": "qtparted",
                "description": "Γραφική εφαρμογή για τη διαχείριση κατατμήσεων σκληρού δίσκου, απαραίτητη για τη συντήρηση και την οργάνωση σταθμών εργασίας δημόσιων φορέων.",
                "commercial_equivalent": "Partition Magic",
                "url": "https://qtparted.sourceforge.net/"
            },
            {
                "id": "osip-gov",
                "title": "Osip",
                "description": "Βιβλιοθήκη ανοικτού κώδικα που υλοποιεί το πρωτόκολλο SIP, επιτρέποντας την ανάπτυξη αυτόνομων και ασφαλών κυβερνητικών υποδομών τηλεφωνίας IP.",
                "commercial_equivalent": "Proprietary SIP Stacks",
                "url": "https://www.gnu.org/software/osip/"
            },
            {
                "id": "i2p-gov",
                "title": "I2P",
                "description": "Ένα πλήρως αποκεντρωμένο δίκτυο ανωνυμίας που επιτρέπει την ασφαλή και ανώνυμη επικοινωνία, ανθεκτικό σε λογοκρισία και παρακολούθηση.",
                "commercial_equivalent": "Closed Darknets / VPNs",
                "url": "https://geti2p.net/"
            },
            {
                "id": "firewalld-gov",
                "title": "FirewallD",
                "description": "Σύγχρονη λύση διαχείρισης τείχους προστασίας για τη θωράκιση των δημόσιων ψηφιακών υποδομών, προσφέροντας ευελιξία και υψηλή διαθεσιμότητα.",
                "commercial_equivalent": "Enterprise Firewall Systems",
                "url": "https://firewalld.org/"
            },
            {
                "id": "dante-gov",
                "title": "Dante",
                "description": "Μια ισχυρή και ελεύθερη υλοποίηση του πρωτοκόλλου SOCKS, που χρησιμοποιείται για την ασφαλή δρομολόγηση και τον έλεγχο της κυκλοφορίας σε κυβερνητικά δίκτυα.",
                "commercial_equivalent": "Microsoft Proxy Server",
                "url": "http://www.inet.no/dante/"
            },
            {
                "id": "ccrtp-gov",
                "title": "Ccrtp",
                "description": "Υλοποίηση της στοίβας πρωτοκόλλων RTP από το έργο GNU, κρίσιμη για τη δημιουργία ασφαλών και σταθερών υποδομών μεταφοράς ήχου και βίντεο σε πραγματικό χρόνο.",
                "commercial_equivalent": "Proprietary RTP Stacks",
                "url": "https://www.gnu.org/software/ccrtp/"
            },
            {
                "id": "ns3-gov",
                "title": "Ns-3",
                "description": "Προσομοιωτής κίνησης δικτύου για τη μελέτη και το σχεδιασμό υποδομών.",
                "commercial_equivalent": "OPNET",
                "url": "https://www.nsnam.org/"
            },
            {
                "id": "gparted-gov",
                "title": "gparted",
                "description": "Εφαρμογή για τη διαμόρφωση και διαχείριση κατατμήσεων σκληρού δίσκου.",
                "commercial_equivalent": "Partition Magic",
                "url": "https://gparted.org/"
            },
            {
                "id": "testdisk-gov",
                "title": "TestDisk / PhotoRec",
                "description": "Εργαλεία για την ανάκτηση χαμένων δεδομένων και την επιδιόρθωση πινάκων κατατμήσεων.",
                "commercial_equivalent": "Εξειδικευμένο λογισμικό ανάκτησης",
                "url": "https://www.cgsecurity.org/"
            }
        ]
    }
]